mkdocs_site_urls/__init__.py
mkdocs_site_urls-0.3.0.dist-info/licenses/LICENSE
tests/__init__.py
tests/test_mkdocs_site_urls.py
mkdocs_site_urls-0.3.0.dist-info/METADATA
mkdocs_site_urls-0.3.0.dist-info/WHEEL
mkdocs_site_urls-0.3.0.dist-info/entry_points.txt
mkdocs_site_urls-0.3.0.dist-info/top_level.txt
mkdocs_site_urls-0.3.0.dist-info/RECORD
