Metadata-Version: 2.4
Name: mkdocs-site-urls
Version: 0.3.0
Summary: A MkDocs plugin that adds support for site-relative URLs
Home-page: https://github.com/OctoPrint/mkdocs-site-urls
Author: Gina Häußge
Author-email: gina@octoprint.org
License: MIT
Project-URL: Source, https://github.com/OctoPrint/mkdocs-site-urls
Keywords: mkdocs,plugin
Requires-Python: >=3.7
License-File: LICENSE
Dynamic: author
Dynamic: author-email
Dynamic: description
Dynamic: description-content-type
Dynamic: home-page
Dynamic: keywords
Dynamic: license
Dynamic: license-file
Dynamic: project-url
Dynamic: requires-python
Dynamic: summary
